{
  "series": {
    "Tutorial Web": [
      "/markdown-examples-copy",
      "/markdown-examples",
      "/en/markdown-examples"
    ],
    "Tutorial Unity": [
      "/unity/tutorial/index.id"
    ],
    "Website": [
      "/website/javasrcript/index"
    ]
  },
  "tags": {
    "web development": [
      "/markdown-examples-copy",
      "/markdown-examples-copy",
      "/markdown-examples",
      "/markdown-examples",
      "/en/markdown-examples",
      "/en/markdown-examples"
    ],
    "vue": [
      "/markdown-examples-copy",
      "/markdown-examples",
      "/en/markdown-examples"
    ],
    "unity": [
      "/unity/tutorial/index.id"
    ],
    "game dev": [
      "/unity/tutorial/index.id"
    ],
    "c#": [
      "/unity/tutorial/index.id"
    ],
    "shader": [
      "/unity/tutorial/index.id"
    ],
    "web dev": [
      "/website/javasrcript/index"
    ],
    "javascript": [
      "/website/javasrcript/index"
    ],
    "node.js": [
      "/website/javasrcript/index"
    ]
  },
  "items": {
    "/markdown-examples-copy": {
      "lang": "id",
      "createdAt": "2022-11-24T00:00:00.000Z",
      "lastUpdated": "2022-12-01T00:00:00.000Z",
      "title": "Roadmap Belajar Unity 2025 Bahasa Indonesia",
      "description": "Ini Cuma Deskripsi",
      "readTime": null,
      "author": [
        {
          "name": "Jianyao17",
          "avatar": "/Jianyao17.png",
          "link": "https://github.com/Jianyao17"
        }
      ],
      "series": "Tutorial Web",
      "order": null,
      "tags": [
        "web development",
        "web development",
        "vue"
      ],
      "thumbnail": "/wallpaperflarecom_wallpaper.jpg",
      "link": "/markdown-examples-copy"
    },
    "/markdown-examples": {
      "lang": "id",
      "createdAt": "2022-11-24T00:00:00.000Z",
      "lastUpdated": "2022-12-01T00:00:00.000Z",
      "title": "Roadmap Belajar Unity 2025 Bahasa Indonesia",
      "description": "Ini Cuma Deskripsi",
      "readTime": null,
      "author": [
        {
          "name": "Jianyao17",
          "avatar": "/Jianyao17.png",
          "link": "https://github.com/Jianyao17"
        }
      ],
      "series": "Tutorial Web",
      "order": null,
      "tags": [
        "web development",
        "web development",
        "vue"
      ],
      "thumbnail": "/wallpaperflarecom_wallpaper.jpg",
      "link": "/markdown-examples"
    },
    "/en/markdown-examples": {
      "lang": "id",
      "createdAt": "2022-11-24T00:00:00.000Z",
      "lastUpdated": "2022-12-01T00:00:00.000Z",
      "title": "Roadmap Belajar Unity 2025 Bahasa Indonesia",
      "description": "Ini Cuma Deskripsi",
      "readTime": null,
      "author": [
        {
          "name": "Jianyao17",
          "avatar": "/Jianyao17.png",
          "link": "https://github.com/Jianyao17"
        }
      ],
      "series": "Tutorial Web",
      "order": null,
      "tags": [
        "web development",
        "web development",
        "vue"
      ],
      "thumbnail": "/en/wallpaperflarecom_wallpaper.jpg",
      "link": "/en/markdown-examples"
    },
    "/unity/tutorial/index.id": {
      "lang": "id-ID",
      "createdAt": "2025-01-13T00:00:00.000Z",
      "lastUpdated": "2025-01-15T00:00:00.000Z",
      "title": "Roadmap Belajar Unity 2025 Bahasa Indonesia",
      "description": "Ini Cuma Deskripsi",
      "readTime": 6,
      "author": [
        {
          "name": "Jianyao17",
          "avatar": "/Jianyao17.png",
          "link": "https://github.com/Jianyao17"
        }
      ],
      "series": "Tutorial Unity",
      "order": 1,
      "tags": [
        "unity",
        "game dev",
        "c#",
        "shader"
      ],
      "thumbnail": "/unity/tutorial/star-rail-kuru.gif",
      "link": "/unity/tutorial/index.id"
    },
    "/website/javasrcript/index": {
      "lang": "in-ID",
      "createdAt": "2025-01-28T00:00:00.000Z",
      "lastUpdated": "2025-01-28T00:00:00.000Z",
      "title": "JavaScript 101",
      "description": "Tutorial JavaScript Pemula",
      "readTime": 5,
      "author": [
        {
          "name": "Jianyao17",
          "avatar": "/Jianyao17.png",
          "link": "https://github.com/Jianyao17"
        }
      ],
      "series": "Website",
      "order": 1,
      "tags": [
        "web dev",
        "javascript",
        "node.js"
      ],
      "thumbnail": null,
      "link": "/website/javasrcript/index"
    }
  }
}